{"etag":"W/\"46ee285d4689a5ca8630ade4676e9761e3995f5a\"","expired":1688481046718,"headers":{"server":"Tengine","content-type":"application/json; charset=utf-8","content-length":"1390","connection":"keep-alive","strict-transport-security":"max-age=5184000","date":"Tue, 04 Jul 2023 14:25:37 GMT","vary":"Origin, Accept, Accept-Encoding","request-id":"a5243260-1a76-11ee-aec6-1d274f5fe6f7","cache-control":"public, max-age=300","x-frame-options":"SAMEORIGIN","x-xss-protection":"1; mode=block","x-content-type-options":"nosniff","x-download-options":"noopen","x-readtime":"1.796","via":"cn1416.l1, kunlun3.cn1416, l2cn3058.l2, cache15.l2cn3058, npmmirror-x86-2022012802003, cache15.l2cn3058[0,0,304-0,H], cache21.l2cn3058[1,0], kunlun10.cn5230[22,22,200-0,H], kunlun5.cn5230[24,0]","etag":"W/\"46ee285d4689a5ca8630ade4676e9761e3995f5a\"","ali-swift-global-savetime":"1688480737","content-encoding":"gzip","age":"9","x-cache":"HIT TCP_REFRESH_HIT dirn:10:362764351","x-swift-savetime":"Tue, 04 Jul 2023 14:25:46 GMT","x-swift-cachetime":"291","timing-allow-origin":"*","eagleid":"6f30472216884807465432683e"},"manifests":{"dist-tags":{"latest":"6.0.0"},"modified":"2022-01-26T13:09:10.419Z","name":"p-locate","versions":{"6.0.0":{"name":"p-locate","version":"6.0.0","dependencies":{"p-limit":"^4.0.0"},"devDependencies":{"ava":"^3.15.0","delay":"^5.0.0","in-range":"^3.0.0","time-span":"^5.0.0","tsd":"^0.17.0","xo":"^0.44.0"},"directories":{},"dist":{"shasum":"3da9a49d4934b901089dca3302fa65dc5a05c04f","size":3069,"noattachment":false,"tarball":"https://registry.npmmirror.com/p-locate/-/p-locate-6.0.0.tgz","integrity":"sha512-wPrq66Llhl7/4AGC6I+cqxT07LhXvWL08LNXz1fENOw0Ap4sRZZ/gZpTTJ5jpurzzzfS2W/Ge9BY3LgLjCShcw=="},"engines":{"node":"^12.20.0 || ^14.13.1 || >=16.0.0"},"_hasShrinkwrap":false},"5.0.0":{"name":"p-locate","version":"5.0.0","dependencies":{"p-limit":"^3.0.2"},"devDependencies":{"ava":"^2.4.0","delay":"^4.1.0","in-range":"^2.0.0","time-span":"^4.0.0","tsd":"^0.13.1","xo":"^0.32.1"},"directories":{},"dist":{"shasum":"83c8315c6785005e3bd021839411c9e110e6d834","size":3151,"noattachment":false,"tarball":"https://registry.npmmirror.com/p-locate/-/p-locate-5.0.0.tgz","integrity":"sha512-LaNjtRWUBY++zB5nE/NwcaoMylSPk+S+ZHNB1TzdbMJMny6dynpAGt7X/tl/QYq3TIeE6nxHppbo2LGymrG5Pw=="},"engines":{"node":">=10"},"_hasShrinkwrap":false},"4.1.0":{"name":"p-locate","version":"4.1.0","dependencies":{"p-limit":"^2.2.0"},"devDependencies":{"ava":"^1.4.1","delay":"^4.1.0","in-range":"^1.0.0","time-span":"^3.0.0","tsd":"^0.7.2","xo":"^0.24.0"},"directories":{},"dist":{"shasum":"a3428bb7088b3a60292f66919278b7c297ad4f07","size":3060,"noattachment":false,"tarball":"https://registry.npmmirror.com/p-locate/-/p-locate-4.1.0.tgz","integrity":"sha512-R79ZZ/0wAxKGu3oYMlz8jy/kbhsNrS7SKZ7PxEHBgJ5+F2mtFW2fK2cOtBh1cHYkQsbzFV7I+EoRKe6Yt0oK7A=="},"engines":{"node":">=8"},"_hasShrinkwrap":false},"4.0.0":{"name":"p-locate","version":"4.0.0","dependencies":{"p-limit":"^2.0.0"},"devDependencies":{"ava":"^1.3.1","delay":"^4.1.0","in-range":"^1.0.0","time-span":"^3.0.0","tsd-check":"^0.3.0","xo":"^0.24.0"},"directories":{},"dist":{"shasum":"fff5d4a5dc4f89babe7d266f6efc685630038651","size":2916,"noattachment":false,"tarball":"https://registry.npmmirror.com/p-locate/-/p-locate-4.0.0.tgz","integrity":"sha512-IvOiDT1hbCdrsFKKXs8AGjxouEfn9VVdz/edtT08IDr+RIn2U/o3Xx+Agx455+CkSRdomMs3EN5BgR2Q0LZX0g=="},"engines":{"node":">=8"},"_hasShrinkwrap":false},"3.0.0":{"name":"p-locate","version":"3.0.0","dependencies":{"p-limit":"^2.0.0"},"devDependencies":{"ava":"*","delay":"^3.0.0","in-range":"^1.0.0","time-span":"^2.0.0","xo":"*"},"directories":{},"dist":{"shasum":"322d69a05c0264b25997d9f40cd8a891ab0064a4","size":2579,"noattachment":false,"tarball":"https://registry.npmmirror.com/p-locate/-/p-locate-3.0.0.tgz","integrity":"sha512-x+12w/To+4GFfgJhBEpiDcLozRJGegY+Ei7/z0tSLkMmxGZNybVMSfWj9aJn8Z5Fc7dBUNJOOVgPv2H7IwulSQ=="},"engines":{"node":">=6"},"_hasShrinkwrap":false},"2.0.0":{"name":"p-locate","version":"2.0.0","dependencies":{"p-limit":"^1.1.0"},"devDependencies":{"ava":"*","delay":"^1.3.1","in-range":"^1.0.0","time-span":"^1.0.0","xo":"*"},"directories":{},"dist":{"shasum":"20a0103b222a70c8fd39cc2e580680f3dde5ec43","size":2580,"noattachment":false,"tarball":"https://registry.npmmirror.com/p-locate/-/p-locate-2.0.0.tgz","integrity":"sha512-nQja7m7gSKuewoVRen45CtVfODR3crN3goVQ0DDZ9N3yHxgpkuBhZqsaiotSQRrADUrne346peY7kT3TSACykg=="},"engines":{"node":">=4"},"_hasShrinkwrap":false},"1.0.0":{"name":"p-locate","version":"1.0.0","dependencies":{"p-map":"^1.1.0"},"devDependencies":{"ava":"*","delay":"^1.3.1","in-range":"^1.0.0","time-span":"^1.0.0","xo":"*"},"directories":{},"dist":{"shasum":"0741476fe43666849508fd0b125778982de716aa","size":2303,"noattachment":false,"tarball":"https://registry.npmmirror.com/p-locate/-/p-locate-1.0.0.tgz","integrity":"sha512-9deoXAv41KrmBdrRoMb4JTiPu05u0VEGkqr6b/9pdLk2ryVRwYmJ42mgR1dpeqlmL6ifuZrSDMvAhBtJGC/dug=="},"engines":{"node":">=4"},"_hasShrinkwrap":false}}}}